coralme/__init__.py
coralme/_version.py
coralme/builder/__init__.py
coralme/builder/auto_blast.sh
coralme/builder/column_format.json
coralme/builder/compartments.py
coralme/builder/curation.py
coralme/builder/dictionaries.py
coralme/builder/dna_replication.py
coralme/builder/flat_files.py
coralme/builder/formulas.py
coralme/builder/gpr.py
coralme/builder/helper_functions.py
coralme/builder/homology.py
coralme/builder/main.py
coralme/builder/modifications.py
coralme/builder/notes.py
coralme/builder/organism.py
coralme/builder/preprocess_inputs.py
coralme/builder/ribosome.py
coralme/builder/transcription.py
coralme/builder/translation.py
coralme/builder/translocation.py
coralme/builder/trna_charging.py
coralme/builder/troubleshooting.py
coralme/core/__init__.py
coralme/core/component.py
coralme/core/model.py
coralme/core/optimization.py
coralme/core/parameters.py
coralme/core/processdata.py
coralme/core/reaction.py
coralme/iJL1678b-ME/BarEven_subsystem_classification.csv
coralme/iJL1678b-ME/minimal-organism.json
coralme/iJL1678b-ME/building_data/RNAs.txt
coralme/iJL1678b-ME/building_data/TUs.txt
coralme/iJL1678b-ME/building_data/TUs_from_biocyc.txt
coralme/iJL1678b-ME/building_data/amino_acid_trna_synthetase.txt
coralme/iJL1678b-ME/building_data/cleaved_methionine.txt
coralme/iJL1678b-ME/building_data/elongation_subreactions.txt
coralme/iJL1678b-ME/building_data/enzyme_reaction_association.txt
coralme/iJL1678b-ME/building_data/excision_machinery.txt
coralme/iJL1678b-ME/building_data/folding_chaperones.txt
coralme/iJL1678b-ME/building_data/folding_dict.txt
coralme/iJL1678b-ME/building_data/generic_dict.txt
coralme/iJL1678b-ME/building_data/genes.txt
coralme/iJL1678b-ME/building_data/genome.gb
coralme/iJL1678b-ME/building_data/iJO1366b.json
coralme/iJL1678b-ME/building_data/initiation_subreactions.txt
coralme/iJL1678b-ME/building_data/keffs.json
coralme/iJL1678b-ME/building_data/keffs.txt
coralme/iJL1678b-ME/building_data/lipid_modifications.txt
coralme-1.2.2.dist-info/licenses/LICENSE
coralme-1.2.2.dist-info/METADATA
coralme-1.2.2.dist-info/WHEEL
coralme-1.2.2.dist-info/entry_points.txt
coralme-1.2.2.dist-info/top_level.txt
coralme-1.2.2.dist-info/RECORD
