Metadata-Version: 2.4
Name: coralME
Version: 1.2.2
Summary: Comprehensive Reconstruction Algorithm for ME-models (coralME)
Home-page: https://github.com/jdtibochab/coralme
Author: Juan D. Tibocha-Bonilla and Rodrigo Santibanez-Palominos
Author-email: "Juan D. Tibocha-Bonilla" <jdtibochab@users.noreply.github.com>, Rodrigo Santibáñez-Palominos <glucksfall@users.noreply.github.com>
License: MIT License
Project-URL: Homepage, https://github.com/jdtibochab/coralme
Project-URL: Manual, https://coralme.readthedocs.io
Project-URL: Bug Reports, https://github.com/jdtibochab/coralme/issues
Project-URL: Source, https://github.com/jdtibochab/coralme
Keywords: metabolism,biology,constraint-based,linear programming,mixed-integer,optimization,flux-balance analysis,reconstruction
Classifier: Development Status :: 5 - Production/Stable
Classifier: Environment :: Console
Classifier: Intended Audience :: Science/Research
Classifier: License :: OSI Approved :: MIT License
Classifier: Operating System :: MacOS
Classifier: Operating System :: Microsoft :: Windows
Classifier: Operating System :: Unix
Classifier: Programming Language :: Python :: 3 :: Only
Classifier: Programming Language :: Python :: 3.8
Classifier: Programming Language :: Python :: 3.9
Classifier: Programming Language :: Python :: 3.10
Classifier: Programming Language :: Python :: 3.11
Classifier: Programming Language :: Python :: 3.12
Classifier: Programming Language :: Python :: 3.13
Classifier: Topic :: Scientific/Engineering :: Bio-Informatics
Requires-Python: ~=3.0
License-File: LICENSE
Requires-Dist: anyconfig
Requires-Dist: anyconfig<0.14.0; python_version <= "3.7"
Requires-Dist: Biopython
Requires-Dist: cobra<=0.28.0; python_version <= "3.7"
Requires-Dist: cobra<=0.29.0; python_version > "3.7"
Requires-Dist: docplex
Requires-Dist: gurobipy<=11; python_version <= "3.12"
Requires-Dist: gurobipy; python_version > "3.12"
Requires-Dist: importlib_resources
Requires-Dist: jsonschema
Requires-Dist: numpy<=1.26.4; python_version <= "3.10"
Requires-Dist: numpy>=2.0.0; python_version > "3.10"
Requires-Dist: openpyxl
Requires-Dist: optlang
Requires-Dist: pandas
Requires-Dist: Pint
Requires-Dist: pyranges<=0.1.1
Requires-Dist: pytest
Requires-Dist: python-libsbml
Requires-Dist: scipy<=1.14.0; python_version <= "3.12"
Requires-Dist: scipy==1.14.1; python_version > "3.12"
Requires-Dist: sympy<=1.12.1
Requires-Dist: tqdm
Requires-Dist: versioneer
Requires-Dist: XlsxWriter
Requires-Dist: ipython
Dynamic: author
Dynamic: home-page
Dynamic: license-file
Dynamic: requires-python
